SaraikiAI/__init__.py
saraikiai-0.0.0.dist-info/METADATA
saraikiai-0.0.0.dist-info/WHEEL
saraikiai-0.0.0.dist-info/top_level.txt
saraikiai-0.0.0.dist-info/RECORD
